iRobot_OI.py
iRobot_OI-0.1.0.dist-info/DESCRIPTION.rst
iRobot_OI-0.1.0.dist-info/METADATA
iRobot_OI-0.1.0.dist-info/RECORD
iRobot_OI-0.1.0.dist-info/WHEEL
iRobot_OI-0.1.0.dist-info/metadata.json
iRobot_OI-0.1.0.dist-info/top_level.txt
